Workbook

Sheet 封面
A2: 德阳市什邡市2个污染地块 土壤污染综合治理项目施工成本测算
A3: 地块：金宏化工、东升实业 · 地点：德阳市什邡市马祖镇 · 规划：公园绿地（非经营性） · 工期12个月
A5: 五表模版：封面 → 费用汇总（工程量×综合单价）→ 综合单价（只含人材机）→ 工料机价格 → 工程量计算。综合单价不含管理费、利润、税金。不引用投资估算单价。
A7: 测算成果
A8: 指标 | B8: 金额 / 指标 | C8: 口径
A9: 含税工程造价（元） | B9: =费用汇总!E59 -> 13293108 | C9: 直接费+管理费+利润+增值税
A10: 含税工程造价（万元） | B10: =费用汇总!F59 -> 1329.3108 | C10: 同上，万元
A11: 人材机直接费（元） | B11: =费用汇总!E54 -> 12291362 | C11: 不含管利税
A12: 企业管理费（元） | B12: =费用汇总!E55 -> 614568.11 | C12: 直接费×5%，不进综合单价
A13: 利润（元） | B13: =费用汇总!E56 -> 0 | C13: 直接费×4%，不进综合单价
A14: 增值税（元） | B14: =费用汇总!E58 -> 387177.91 | C14: 税前×9%
A15: 清挖方量（m³） | B15: =工程量计算!C4 -> 33728.15 | C15: 可研1.1.3
A16: 水泥窑吨位（t） | B16: =工程量计算!C38 -> 27241.136 | C16: 方量×容重1.6
A17: 含汞方量（m³） | B17: =工程量计算!C7 -> 202.65 | C17: 安全处置
A18: 勾稽差（m³） | B18: =工程量计算!C46+工程量计算!C47 -> 0 | C18: 两项均应为0
A20: 口径
A21: 1. 范围：施工成本。不含前期咨询、勘察、初步设计、施工图预算、环境监理、效果评估、招标代理、预备费、建设单位管理费。
A22: 2. 工程量取自可研1.1.3、表4.3-1和表13.1-1的数量列。投资估算中的单价、费用构成、取费基数一律不引用、不对标、不反推。
A23: 3. 技术路线（可研第6章）：清挖筛分，卵石冲洗后回填，含汞土壤安全处置，其余污染土壤水泥窑协同处置，外购清洁土回填。基坑支护和降水可研明确未设计，本表不含。
A24: 4. 水泥窑190元/t不含运，来自成本库「旺平-水泥窑协同处置-不含运-元-t」，用户已确认。运费按0.80元/t·km×运距单列。运距40 km为假设。
A25: 5. 含汞处置2800元/m³，来自成本库「含汞污染土壤安全处置-元-m3」（川发改价格〔2011〕1776号口径）。接收单位未定。
A26: 6. 外购清洁土80元/m³为什邡周边到场估价，不套用雅安45元/m³。废水系数0.15、容重1.6为假设，黄色可改。
A27: 7. 污染物：砷(As)、汞(Hg)、铅(Pb)、镉(Cd)、铜(Cu)、铬（六价）(Cr(VI))。修复目标值见可研表4.2-1，与GB 36600-2018第一类用地筛选值不是同一套数。
A28: 8. 金额单位元，不含税单价。蓝色黄底为输入，绿色为跨表引用，黑色为公式。
A29: 9. 已补回填土壤监测40个、二次污染区域20个。全项检测库内无独立价，暂用150元/样，不采用可研2800元/个。场内地磅2台（两地块各1台，100 t），设备摊销28000元/台为估价，另加混凝土基础。不是地泵，也不与进厂过磅12元/t重复。

Sheet 费用汇总
A1: 费用汇总。上半是工程量×工序综合单价。下半管理费、利润、税金不进综合单价。不含可研其他费和预备费。不引用投资估算单价。
A2: 工程量G列引用工程量计算；综合单价H列引用综合单价P列。改黄色消耗量、资源单价或本表费率后，合价和图表一起变。
A3: 序号 | B3: 分部 | C3: 编码 | D3: 项目名称 | E3: 工序特征 | F3: 单位 | G3: 工程量 | H3: 综合单价 | I3: 合价（元） | J3: 单价位置 | K3: 依据
A4: 1 | B4: A临建 | C4: SF01 | D4: 测量放线 | E4: 拐点、分层标高 | F4: 项 | G4: 1 | H4: =综合单价!P4 -> 10400 | I4: =G4*H4 -> 10400 | J4: 综合单价!P4 | K4: 可研2.1.1.1只取工作内容
A5: 2 | B5: A临建 | C5: SF02 | D5: 临时施工便道 | E5: 宽4 m，碎石+混凝土 | F5: m | G5: =工程量计算!C16 -> 100 | H5: =综合单价!P7 -> 294.2946 | I5: =G5*H5 -> 29429.46 | J5: 综合单价!P7 | K5: T13，只取长度
A6: 3 | B6: A临建 | C6: SF03 | D6: 洗车池 | E6: 5 m×20 m平台+沉淀 | F6: 座 | G6: =工程量计算!C17 -> 2 | H6: =综合单价!P13 -> 15162.55 | I6: =G6*H6 -> 30325.1 | J6: 综合单价!P13 | K6: T14
A7: 4 | B7: A临建 | C7: SF04 | D7: 临时阻隔围挡 | E7: 2 m彩钢，12个月 | F7: m | G7: =工程量计算!C18 -> 800 | H7: =综合单价!P20 -> 108.6418 | I7: =G7*H7 -> 86913.44 | J7: 综合单价!P20 | K7: T15
A8: 5 | B8: A临建 | C8: SF05 | D8: 修复场所防渗地面 | E8: 两布一膜+15 cm混凝土 | F8: m² | G8: =工程量计算!C19 -> 5000 | H8: =综合单价!P25 -> 85.50995 | I8: =G8*H8 -> 427549.75 | J8: 综合单价!P25 | K8: T16
A9: 6 | B9: A临建 | C9: SF06 | D9: 办公生活板房 | E9: 岩棉夹芯板安拆 | F9: m² | G9: =工程量计算!C15 -> 500 | H9: =综合单价!P32 -> 473.6918 | I9: =G9*H9 -> 236845.9 | J9: 综合单价!P32 | K9: T12
A10: 7 | B10: A临建 | C10: SF22 | D10: 防尘网铺设 | E10: 材料+铺设 | F10: m² | G10: =工程量计算!C20 -> 13000 | H10: =综合单价!P93 -> 3.825 | I10: =G10*H10 -> 49725 | J10: 综合单价!P93 | K10: T17
A11: 8 | B11: A临建 | C11: SF23 | D11: 地表导排沟 | E11: 0.3×0.3 m砖沟 | F11: m | G11: =工程量计算!C21 -> 800 | H11: =综合单价!P96 -> 85.1199 | I11: =G11*H11 -> 68095.92 | J11: 综合单价!P96 | K11: T18
A12: 9 | B12: A临建 | C12: SF24 | D12: 集水池 | E12: 4×10×3 m砖砌 | F12: 座 | G12: =工程量计算!C22 -> 2 | H12: =综合单价!P102 -> 15486.8 | I12: =G12*H12 -> 30973.6 | J12: 综合单价!P102 | K12: T19
A13: 10 | B13: A临建 | C13: SF25 | D13: 标识标牌 | E13: 铝板反光 | F13: 个 | G13: =工程量计算!C23 -> 20 | H13: =综合单价!P109 -> 242.25 | I13: =G13*H13 -> 4845 | J13: 综合单价!P109 | K13: T20
A14: 11 | B14: A临建 | C14: SF27 | D14: 机械进出场 | E14: 4台机械 | F14: 项 | G14: 1 | H14: =综合单价!P116 -> 11765.8 | I14: =G14*H14 -> 11765.8 | J14: 综合单价!P116 | K14: 工序
A15: 12 | B15: B清挖筛分 | C15: SF07 | D15: 污染土壤清挖及场内短驳 | E15: 120 m³/台班+场内200 m | F15: m³ | G15: =工程量计算!C4 -> 33728.15 | H15: =综合单价!P38 -> 24.53829 | I15: =G15*H15 -> 827631.13 | J15: 综合单价!P38 | K15: T01
A16: 13 | B16: B清挖筛分 | C16: SF08 | D16: 筛分破碎 | E16: 阿鲁斗至进窑粒径 | F16: m³ | G16: =工程量计算!C4 -> 33728.15 | H16: =综合单价!P42 -> 21.9063 | I16: =G16*H16 -> 738858.97 | J16: 综合单价!P42 | K16: T01全量过筛
A17: 14 | B17: C处置 | C17: SF09 | D17: 砂卵石清洗 | E17: 不含废水 | F17: m³ | G17: =工程量计算!C5 -> 16499.79 | H17: =综合单价!P47 -> 17.2428 | I17: =G17*H17 -> 284502.58 | J17: 综合单价!P47 | K17: T02
A18: 15 | B18: C处置 | C18: SF15 | D18: 含汞污染土壤安全处置 | E18: 不含运 | F18: m³ | G18: =工程量计算!C7 -> 202.65 | H18: =综合单价!P67 -> 2800 | I18: =G18*H18 -> 567420 | J18: 综合单价!P67 | K18: T04
A19: 16 | B19: C处置 | C19: SF13 | D19: 水泥窑协同处置 | E19: 不含运190元/t | F19: t | G19: =工程量计算!C38 -> 27241.136 | H19: =综合单价!P62 -> 190 | I19: =G19*H19 -> 5175815.8 | J19: 综合单价!P62 | K19: D01
A20: 17 | B20: D运输 | C20: SF14 | D20: 水泥窑密闭运输 | E20: 0.80元/t·km×运距 | F20: t | G20: =工程量计算!C38 -> 27241.136 | H20: =综合单价!P64 -> 44 | I20: =G20*H20 -> 1198610 | J20: 综合单价!P64 | K20: D01
A21: 18 | B21: D运输 | C21: SF16 | D21: 含汞密闭运输 | E21: 0.80元/t·km×含汞运距 | F21: t | G21: =工程量计算!C39 -> 324.24 | H21: =综合单价!P69 -> 76 | I21: =G21*H21 -> 24642.24 | J21: 综合单价!P69 | K21: D02
A22: 19 | B22: E回填 | C22: SF17 | D22: 清洗后砂卵石回填 | E22: 短驳+碾压 | F22: m³ | G22: =工程量计算!C5 -> 16499.79 | H22: =综合单价!P72 -> 13.1302 | I22: =G22*H22 -> 216645.54 | J22: 综合单价!P72 | K22: T02
A23: 20 | B23: E回填 | C23: SF18 | D23: 外购清洁土 | E23: 什邡到场 | F23: m³ | G23: =工程量计算!C44 -> 17228.36 | H23: =综合单价!P77 -> 80 | I23: =G23*H23 -> 1378268.8 | J23: 综合单价!P77 | K23: D07
A24: 21 | B24: E回填 | C24: SF19 | D24: 清洁土分层回填压实 | E24: 分层≤300 mm | F24: m³ | G24: =工程量计算!C44 -> 17228.36 | H24: =综合单价!P79 -> 11.39355 | I24: =G24*H24 -> 196292.18 | J24: 综合单价!P79 | K24: D07
A25: 22 | B25: F废水 | C25: SF10 | D25: 卵石清洗废水预处理 | E25: 混凝沉淀运行 | F25: m³ | G25: =工程量计算!C43 -> 2474.9685 | H25: =综合单价!P52 -> 4.787 | I25: =G25*H25 -> 11847.674 | J25: 综合单价!P52 | K25: D06
A26: 23 | B26: F废水 | C26: SF11 | D26: 预处理后废水外运 | E26: 场外短运 | F26: m³ | G26: =工程量计算!C43 -> 2474.9685 | H26: =综合单价!P57 -> 46.966 | I26: =G26*H26 -> 116239.37 | J26: 综合单价!P57 | K26: D06
A27: 24 | B27: F废水 | C27: SF12 | D27: 工业污水厂接收 | E27: 成本库75元/m³ | F27: m³ | G27: =工程量计算!C43 -> 2474.9685 | H27: =综合单价!P60 -> 75 | I27: =G27*H27 -> 185622.64 | J27: 综合单价!P60 | K27: D06
A28: 25 | B28: G措施 | C28: SF26 | D28: 安全文明及降尘 | E28: 12个月 | F28: 项 | G28: 1 | H28: =综合单价!P113 -> 100740 | I28: =G28*H28 -> 100740 | J28: 综合单价!P113 | K28: 工序
A29: 26 | B29: H监测 | C29: SF20 | D29: 地下水监测井成井 | E29: 深20 m | F29: 口 | G29: =工程量计算!C24 -> 10 | H29: =综合单价!P84 -> 6969.04 | I29: =G29*H29 -> 69690.4 | J29: 综合单价!P84 | K29: T21
A30: 27 | B30: H监测 | C30: SF21 | D30: 地下水长期监测 | E30: 铅，外委 | F30: 样 | G30: =工程量计算!C30 -> 40 | H30: =综合单价!P91 -> 1200 | I30: =G30*H30 -> 48000 | J30: 综合单价!P91 | K30: T27
A31: 28 | B31: H监测 | C31: SF28 | D31: 大气监测 | E31: 外委 | F31: 点次 | G31: =工程量计算!C26 -> 54 | H31: =综合单价!P120 -> 750 | I31: =G31*H31 -> 40500 | J31: 综合单价!P120 | K31: T23
A32: 29 | B32: H监测 | C32: SF29 | D32: 噪声监测 | E32: 外委 | F32: 点次 | G32: =工程量计算!C27 -> 36 | H32: =综合单价!P122 -> 200 | I32: =G32*H32 -> 7200 | J32: 综合单价!P122 | K32: T24
A33: 30 | B33: H监测 | C33: SF30 | D33: 基坑清理效果自检 | E33: 超标因子 | F33: 个 | G33: =工程量计算!C28 -> 154 | H33: =综合单价!P124 -> 150 | I33: =G33*H33 -> 23100 | J33: 综合单价!P124 | K33: T25
A34: 31 | B34: H监测 | C34: SF31 | D34: 卵石清洗效果自检 | E34: 超标因子 | F34: 个 | G34: =工程量计算!C29 -> 38 | H34: =综合单价!P126 -> 150 | I34: =G34*H34 -> 5700 | J34: 综合单价!P126 | K34: T26
A35: 32 | B35: A临建 | C35: SF32 | D35: 场内地磅 | E35: 100 t汽车衡，两地块各1台 | F35: 台 | G35: =工程量计算!C35 -> 2 | H35: =综合单价!P128 -> 39082.95 | I35: =G35*H35 -> 78165.9 | J35: 综合单价!P128 | K35: 不是地泵，也不是进厂过磅杂费
A36: 33 | B36: H监测 | C36: SF33 | D36: 回填土壤监测 | E36: 45项+石油烃，施工自检 | F36: 个 | G36: =工程量计算!C33 -> 40 | H36: =综合单价!P134 -> 150 | I36: =G36*H36 -> 6000 | J36: 综合单价!P134 | K36: T30，不取可研2800元/个
A37: 34 | B37: H监测 | C37: SF34 | D37: 二次污染区域监测 | E37: 潜在二次污染区，施工自检 | F37: 个 | G37: =工程量计算!C34 -> 20 | H37: =综合单价!P136 -> 150 | I37: =G37*H37 -> 3000 | J37: 综合单价!P136 | K37: T31，不取可研2800元/个
D38: 人材机直接费合计 | I38: =SUM(I4:I37) -> 12291362
A40: 分部小计（图表数据）
A41: 分部 | B41: 合价（元） | C41: 占直接费
A42: A临建 | B42: =SUMIF($B$4:$B$37,A42,$I$4:$I$37) -> 1065034.9 | C42: =IF($I$38=0,0,B42/$I$38) -> 0.086649051
A43: B清挖筛分 | B43: =SUMIF($B$4:$B$37,A43,$I$4:$I$37) -> 1566490.1 | C43: =IF($I$38=0,0,B43/$I$38) -> 0.12744642
A44: C处置 | B44: =SUMIF($B$4:$B$37,A44,$I$4:$I$37) -> 6027738.4 | C44: =IF($I$38=0,0,B44/$I$38) -> 0.49040442
A45: D运输 | B45: =SUMIF($B$4:$B$37,A45,$I$4:$I$37) -> 1223252.2 | C45: =IF($I$38=0,0,B45/$I$38) -> 0.09952129
A46: E回填 | B46: =SUMIF($B$4:$B$37,A46,$I$4:$I$37) -> 1791206.5 | C46: =IF($I$38=0,0,B46/$I$38) -> 0.14572889
A47: F废水 | B47: =SUMIF($B$4:$B$37,A47,$I$4:$I$37) -> 313709.68 | C47: =IF($I$38=0,0,B47/$I$38) -> 0.025522776
A48: G措施 | B48: =SUMIF($B$4:$B$37,A48,$I$4:$I$37) -> 100740 | C48: =IF($I$38=0,0,B48/$I$38) -> 0.0081959996
A49: H监测 | B49: =SUMIF($B$4:$B$37,A49,$I$4:$I$37) -> 203190.4 | C49: =IF($I$38=0,0,B49/$I$38) -> 0.016531154
A50: 分部校核 | B50: =SUM(B42:B49) -> 12291362 | C50: =SUM(C42:C49) -> 1
A52: 取费（黄底费率可改，不进综合单价）
A53: 序号 | B53: 费用名称 | C53: 计算基数 | D53: 费率 | E53: 金额（元） | F53: 金额（万元） | G53: 备注
A54: 一 | B54: 人材机直接费 | C54: 清单合价 | D54: — | E54: =I38 -> 12291362 | F54: =E54/10000 -> 1229.1362 | G54: 不含管利税
A55: 二 | B55: 企业管理费 | C55: 直接费×费率 | D55: 0.05 | E55: =E54*D55 -> 614568.11 | F55: =E55/10000 -> 61.456811 | G55: 不进综合单价。默认5%
A56: 三 | B56: 利润 | C56: 直接费×费率 | D56: 0 | E56: =E54*D56 -> 0 | F56: =E56/10000 -> 0 | G56: 不进综合单价。按直接费4%，不是按直接费+管理费
A57: 四 | B57: 税前造价 | C57: 直接费+管理费+利润 | D57: — | E57: =E54+E55+E56 -> 12905930 | F57: =E57/10000 -> 1290.593 | G57: 增值税计税基数
A58: 五 | B58: 增值税 | C58: 税前×税率 | D58: 3.0% | E58: =E57*D58 -> 387177.91 | F58: =E58/10000 -> 38.717791 | G58: 建筑服务一般计税9%，川建造价发〔2019〕181号口径
A59: 六 | B59: 含税工程造价 | C59: 税前+增值税 | D59: — | E59: =E57+E58 -> 13293108 | F59: =E59/10000 -> 1329.3108 | G59: 本次测算成果。不含可研其他费和预备费
A61: 可研总投资4805.43万元、工程直接费3943.51万元只说明投资口径，不参与本表组价，也不作为单价来源。差额不在本表计算，避免把投资估算价格引进公式。

Sheet 综合单价
A1: 综合单价（只含人材机）。消耗量按工序计算，单价VLOOKUP工料机。不使用投资估算单价，管理费、利润、税金不进本表。
A2: 黄底为消耗量。台班单价是工料机表的公式结果。外委仅水泥窑、含汞处置、外购土、污水厂接收和监测化验。改消耗量或资源单价后，P列综合单价自动重算。
A3: 序号 | B3: 清单编码 | C3: 项目名称 | D3: 单位 | E3: 行类 | F3: 资源编码 | G3: 资源名称 | H3: 消耗单位 | I3: 消耗量 | J3: 单价 | K3: 合价 | L3: 人工 | M3: 材料 | N3: 机械 | O3: 工序说明 | P3: 综合单价
A4: 1 | B4: SF01 | C4: 测量放线 | D4: 项 | E4: 汇总 | K4: =SUM(K5:K6) -> 10400 | L4: =SUMIF(E5:E6,"人工",K5:K6) -> 10400 | M4: =SUMIF(E5:E6,"材料",K5:K6) -> 0 | N4: =SUMIF(E5:E6,"机械",K5:K6)+SUMIF(E5:E6,"外委",K5:K6) -> 0 | O4: 两地块拐点、分层标高、竣工测量 | P4: =K4 -> 10400
A5: 1.1 | B5: SF01 | C5: 测量放线 | D5: 项 | E5: 人工 | F5: L02 | G5: 技术工/带班 | H5: 工日 | I5: 16 | J5: =IFERROR(VLOOKUP(F5,工料机价格!$A$4:$F$45,6,FALSE()),0) -> 350 | K5: =I5*J5 -> 5600 | L5: =IF(E5="人工",K5,0) -> 5600 | M5: =IF(E5="材料",K5,0) -> 0 | N5: =IF(OR(E5="机械",E5="外委"),K5,0) -> 0 | O5: 测量工程师
A6: 1.2 | B6: SF01 | C6: 测量放线 | D6: 项 | E6: 人工 | F6: L01 | G6: 普通工 | H6: 工日 | I6: 16 | J6: =IFERROR(VLOOKUP(F6,工料机价格!$A$4:$F$45,6,FALSE()),0) -> 300 | K6: =I6*J6 -> 4800 | L6: =IF(E6="人工",K6,0) -> 4800 | M6: =IF(E6="材料",K6,0) -> 0 | N6: =IF(OR(E6="机械",E6="外委"),K6,0) -> 0 | O6: 司尺
A7: 2 | B7: SF02 | C7: 临时施工便道 | D7: m | E7: 汇总 | K7: =SUM(K8:K12) -> 294.2946 | L7: =SUMIF(E8:E12,"人工",K8:K12) -> 12 | M7: =SUMIF(E8:E12,"材料",K8:K12) -> 269.4 | N7: =SUMIF(E8:E12,"机械",K8:K12)+SUMIF(E8:E12,"外委",K8:K12) -> 12.8946 | O7: 宽4 m：20 cm碎石+15 cm混凝土，不采用可研350元/m | P7: =K7 -> 294.2946
A8: 2.1 | B8: SF02 | C8: 临时施工便道 | D8: m | E8: 人工 | F8: L01 | G8: 普通工 | H8: 工日 | I8: 0.04 | J8: =IFERROR(VLOOKUP(F8,工料机价格!$A$4:$F$45,6,FALSE()),0) -> 300 | K8: =I8*J8 -> 12 | L8: =IF(E8="人工",K8,0) -> 12 | M8: =IF(E8="材料",K8,0) -> 0 | N8: =IF(OR(E8="机械",E8="外委"),K8,0) -> 0 | O8: 整平、铺筑
A9: 2.2 | B9: SF02 | C9: 临时施工便道 | D9: m | E9: 材料 | F9: AGG | G9: 级配碎石 | H9: m³ | I9: 0.8 | J9: =IFERROR(VLOOKUP(F9,工料机价格!$A$4:$F$45,6,FALSE()),0) -> 78 | K9: =I9*J9 -> 62.4 | L9: =IF(E9="人工",K9,0) -> 0 | M9: =IF(E9="材料",K9,0) -> 62.4 | N9: =IF(OR(E9="机械",E9="外委"),K9,0) -> 0 | O9: 4 m×0.20 m
A10: 2.3 | B10: SF02 | C10: 临时施工便道 | D10: m | E10: 材料 | F10: C20 | G10: C20商品混凝土 | H10: m³ | I10: 0.6 | J10: =IFERROR(VLOOKUP(F10,工料机价格!$A$4:$F$45,6,FALSE()),0) -> 345 | K10: =I10*J10 -> 207 | L10: =IF(E10="人工",K10,0) -> 0 | M10: =IF(E10="材料",K10,0) -> 207 | N10: =IF(OR(E10="机械",E10="外委"),K10,0) -> 0 | O10: 4 m×0.15 m
A11: 2.4 | B11: SF02 | C11: 临时施工便道 | D11: m | E11: 机械 | F11: LDR | G11: 装载机50型台班 | H11: 台班 | I11: 0.006 | J11: =IFERROR(VLOOKUP(F11,工料机价格!$A$4:$F$45,6,FALSE()),0) -> 1445.9 | K11: =I11*J11 -> 8.6754 | L11: =IF(E11="人工",K11,0) -> 0 | M11: =IF(E11="材料",K11,0) -> 0 | N11: =IF(OR(E11="机械",E11="外委"),K11,0) -> 8.6754 | O11: 摊铺
A12: 2.5 | B12: SF02 | C12: 临时施工便道 | D12: m | E12: 机械 | F12: RL | G12: 压路机台班 | H12: 台班 | I12: 0.004 | J12: =IFERROR(VLOOKUP(F12,工料机价格!$A$4:$F$45,6,FALSE()),0) -> 1054.8 | K12: =I12*J12 -> 4.2192 | L12: =IF(E12="人工",K12,0) -> 0 | M12: =IF(E12="材料",K12,0) -> 0 | N12: =IF(OR(E12="机械",E12="外委"),K12,0) -> 4.2192 | O12: 碾压
A13: 3 | B13: SF03 | C13: 洗车池 | D13: 座 | E13: 汇总 | K13: =SUM(K14:K19) -> 15162.55 | L13: =SUMIF(E14:E19,"人工",K14:K19) -> 4300 | M13: =SUMIF(E14:E19,"材料",K14:K19) -> 9975.9 | N13: =SUMIF(E14:E19,"机械",K14:K19)+SUMIF(E14:E19,"外委",K14:K19) -> 886.65 | O13: 平台5×20×0.25 m钢筋混凝土+砖砌沉淀，不采用可研2万元/座 | P13: =K13 -> 15162.55
A14: 3.1 | B14: SF03 | C14: 洗车池 | D14: 座 | E14: 人工 | F14: L01 | G14: 普通工 | H14: 工日 | I14: 12 | J14: =IFERROR(VLOOKUP(F14,工料机价格!$A$4:$F$45,6,FALSE()),0) -> 300 | K14: =I14*J14 -> 3600 | L14: =IF(E14="人工",K14,0) -> 3600 | M14: =IF(E14="材料",K14,0) -> 0 | N14: =IF(OR(E14="机械",E14="外委"),K14,0) -> 0 | O14: 支模、砌筑
A15: 3.2 | B15: SF03 | C15: 洗车池 | D15: 座 | E15: 人工 | F15: L02 | G15: 技术工/带班 | H15: 工日 | I15: 2 | J15: =IFERROR(VLOOKUP(F15,工料机价格!$A$4:$F$45,6,FALSE()),0) -> 350 | K15: =I15*J15 -> 700 | L15: =IF(E15="人工",K15,0) -> 700 | M15: =IF(E15="材料",K15,0) -> 0 | N15: =IF(OR(E15="机械",E15="外委"),K15,0) -> 0 | O15: 钢筋
A16: 3.3 | B16: SF03 | C16: 洗车池 | D16: 座 | E16: 材料 | F16: WASHB | G16: 洗车池砖砌沉淀体 | H16: 座 | I16: 1 | J16: =IFERROR(VLOOKUP(F16,工料机价格!$A$4:$F$45,6,FALSE()),0) -> 990.9 | K16: =I16*J16 -> 990.9 | L16: =IF(E16="人工",K16,0) -> 0 | M16: =IF(E16="材料",K16,0) -> 990.9 | N16: =IF(OR(E16="机械",E16="外委"),K16,0) -> 0 | O16: 砖+砂浆公式
A17: 3.4 | B17: SF03 | C17: 洗车池 | D17: 座 | E17: 材料 | F17: C20 | G17: C20商品混凝土 | H17: m³ | I17: 25 | J17: =IFERROR(VLOOKUP(F17,工料机价格!$A$4:$F$45,6,FALSE()),0) -> 345 | K17: =I17*J17 -> 8625 | L17: =IF(E17="人工",K17,0) -> 0 | M17: =IF(E17="材料",K17,0) -> 8625 | N17: =IF(OR(E17="机械",E17="外委"),K17,0) -> 0 | O17: 5×20×0.25
A18: 3.5 | B18: SF03 | C18: 洗车池 | D18: 座 | E18: 材料 | F18: HDPE | G18: HDPE防渗膜1.5mm | H18: m² | I18: 30 | J18: =IFERROR(VLOOKUP(F18,工料机价格!$A$4:$F$45,6,FALSE()),0) -> 12 | K18: =I18*J18 -> 360 | L18: =IF(E18="人工",K18,0) -> 0 | M18: =IF(E18="材料",K18,0) -> 360 | N18: =IF(OR(E18="机械",E18="外委"),K18,0) -> 0 | O18: 沉淀池内衬
A19: 3.6 | B19: SF03 | C19: 洗车池 | D19: 座 | E19: 机械 | F19: EXC | G19: 挖掘机1.0m³台班 | H19: 台班 | I19: 0.5 | J19: =IFERROR(VLOOKUP(F19,工料机价格!$A$4:$F$45,6,FALSE()),0) -> 1773.3 | K19: =I19*J19 -> 886.65 | L19: =IF(E19="人工",K19,0) -> 0 | M19: =IF(E19="材料",K19,0) -> 0 | N19: =IF(OR(E19="机械",E19="外委"),K19,0) -> 886.65 | O19: 基坑
A20: 4 | B20: SF04 | C20: 临时阻隔围挡 | D20: m | E20: 汇总 | K20: =SUM(K21:K24) -> 108.6418 | L20: =SUMIF(E21:E24,"人工",K21:K24) -> 24 | M20: =SUMIF(E21:E24,"材料",K21:K24) -> 77.55 | N20: =SUMIF(E21:E24,"机械",K21:K24)+SUMIF(E21:E24,"外委",K21:K24) -> 7.0918 | O20: 2 m彩钢含基础，12个月，不采用可研100元/m | P20: =K20 -> 108.6418
A21: 4.1 | B21: SF04 | C21: 临时阻隔围挡 | D21: m | E21: 人工 | F21: L01 | G21: 普通工 | H21: 工日 | I21: 0.08 | J21: =IFERROR(VLOOKUP(F21,工料机价格!$A$4:$F$45,6,FALSE()),0) -> 300 | K21: =I21*J21 -> 24 | L21: =IF(E21="人工",K21,0) -> 24 | M21: =IF(E21="材料",K21,0) -> 0 | N21: =IF(OR(E21="机械",E21="外委"),K21,0) -> 0 | O21: 安拆
A22: 4.2 | B22: SF04 | C22: 临时阻隔围挡 | D22: m | E22: 材料 | F22: CSP | G22: 彩钢板 | H22: m² | I22: 2.1 | J22: =IFERROR(VLOOKUP(F22,工料机价格!$A$4:$F$45,6,FALSE()),0) -> 32 | K22: =I22*J22 -> 67.2 | L22: =IF(E22="人工",K22,0) -> 0 | M22: =IF(E22="材料",K22,0) -> 67.2 | N22: =IF(OR(E22="机械",E22="外委"),K22,0) -> 0 | O22: 2 m高加损耗
A23: 4.3 | B23: SF04 | C23: 临时阻隔围挡 | D23: m | E23: 材料 | F23: C20 | G23: C20商品混凝土 | H23: m³ | I23: 0.03 | J23: =IFERROR(VLOOKUP(F23,工料机价格!$A$4:$F$45,6,FALSE()),0) -> 345 | K23: =I23*J23 -> 10.35 | L23: =IF(E23="人工",K23,0) -> 0 | M23: =IF(E23="材料",K23,0) -> 10.35 | N23: =IF(OR(E23="机械",E23="外委"),K23,0) -> 0 | O23: 基础
A24: 4.4 | B24: SF04 | C24: 临时阻隔围挡 | D24: m | E24: 机械 | F24: CRN | G24: 汽车吊25t台班 | H24: 台班 | I24: 0.004 | J24: =IFERROR(VLOOKUP(F24,工料机价格!$A$4:$F$45,6,FALSE()),0) -> 1772.95 | K24: =I24*J24 -> 7.0918 | L24: =IF(E24="人工",K24,0) -> 0 | M24: =IF(E24="材料",K24,0) -> 0 | N24: =IF(OR(E24="机械",E24="外委"),K24,0) -> 7.0918 | O24: 安拆
A25: 5 | B25: SF05 | C25: 修复场所防渗地面 | D25: m² | E25: 汇总 | K25: =SUM(K26:K31) -> 85.50995 | L25: =SUMIF(E26:E31,"人工",K26:K31) -> 7.4 | M25: =SUMIF(E26:E31,"材料",K26:K31) -> 75.45 | N25: =SUMIF(E26:E31,"机械",K26:K31)+SUMIF(E26:E31,"外委",K26:K31) -> 2.65995 | O25: 两布一膜+15 cm混凝土。膜为库内1.5 mm，可研写2.0 mm+300 mm黏土，黏土未另计 | P25: =K25 -> 85.50995
A26: 5.1 | B26: SF05 | C26: 修复场所防渗地面 | D26: m² | E26: 人工 | F26: L01 | G26: 普通工 | H26: 工日 | I26: 0.02 | J26: =IFERROR(VLOOKUP(F26,工料机价格!$A$4:$F$45,6,FALSE()),0) -> 300 | K26: =I26*J26 -> 6 | L26: =IF(E26="人工",K26,0) -> 6 | M26: =IF(E26="材料",K26,0) -> 0 | N26: =IF(OR(E26="机械",E26="外委"),K26,0) -> 0 | O26: 铺膜、浇筑
A27: 5.2 | B27: SF05 | C27: 修复场所防渗地面 | D27: m² | E27: 人工 | F27: L02 | G27: 技术工/带班 | H27: 工日 | I27: 0.004 | J27: =IFERROR(VLOOKUP(F27,工料机价格!$A$4:$F$45,6,FALSE()),0) -> 350 | K27: =I27*J27 -> 1.4 | L27: =IF(E27="人工",K27,0) -> 1.4 | M27: =IF(E27="材料",K27,0) -> 0 | N27: =IF(OR(E27="机械",E27="外委"),K27,0) -> 0 | O27: 焊接
A28: 5.3 | B28: SF05 | C28: 修复场所防渗地面 | D28: m² | E28: 材料 | F28: GT | G28: 土工布400g | H28: m² | I28: 2.1 | J28: =IFERROR(VLOOKUP(F28,工料机价格!$A$4:$F$45,6,FALSE()),0) -> 5 | K28: =I28*J28 -> 10.5 | L28: =IF(E28="人工",K28,0) -> 0 | M28: =IF(E28="材料",K28,0) -> 10.5 | N28: =IF(OR(E28="机械",E28="外委"),K28,0) -> 0 | O28: 上下两层，库内400 g
A29: 5.4 | B29: SF05 | C29: 修复场所防渗地面 | D29: m² | E29: 材料 | F29: HDPE | G29: HDPE防渗膜1.5mm | H29: m² | I29: 1.1 | J29: =IFERROR(VLOOKUP(F29,工料机价格!$A$4:$F$45,6,FALSE()),0) -> 12 | K29: =I29*J29 -> 13.2 | L29: =IF(E29="人工",K29,0) -> 0 | M29: =IF(E29="材料",K29,0) -> 13.2 | N29: =IF(OR(E29="机械",E29="外委"),K29,0) -> 0 | O29: 库内1.5 mm，不是可研2.0 mm包干
A30: 5.5 | B30: SF05 | C30: 修复场所防渗地面 | D30: m² | E30: 材料 | F30: C20 | G30: C20商品混凝土 | H30: m³ | I30: 0.15 | J30: =IFERROR(VLOOKUP(F30,工料机价格!$A$4:$F$45,6,FALSE()),0) -> 345 | K30: =I30*J30 -> 51.75 | L30: =IF(E30="人工",K30,0) -> 0 | M30: =IF(E30="材料",K30,0) -> 51.75 | N30: =IF(OR(E30="机械",E30="外委"),K30,0) -> 0 | O30: 保护层
A31: 5.6 | B31: SF05 | C31: 修复场所防渗地面 | D31: m² | E31: 机械 | F31: EXC | G31: 挖掘机1.0m³台班 | H31: 台班 | I31: 0.0015 | J31: =IFERROR(VLOOKUP(F31,工料机价格!$A$4:$F$45,6,FALSE()),0) -> 1773.3 | K31: =I31*J31 -> 2.65995 | L31: =IF(E31="人工",K31,0) -> 0 | M31: =IF(E31="材料",K31,0) -> 0 | N31: =IF(OR(E31="机械",E31="外委"),K31,0) -> 2.65995 | O31: 整平
A32: 6 | B32: SF06 | C32: 办公生活板房 | D32: m² | E32: 汇总 | K32: =SUM(K33:K37) -> 473.6918 | L32: =SUMIF(E33:E37,"人工",K33:K37) -> 43 | M32: =SUMIF(E33:E37,"材料",K33:K37) -> 423.6 | N32: =SUMIF(E33:E37,"机械",K33:K37)+SUMIF(E33:E37,"外委",K33:K37) -> 7.0918 | O32: 岩棉夹芯板安拆一次，12个月。不采用可研600元/m²买断 | P32: =K32 -> 473.6918
A33: 6.1 | B33: SF06 | C33: 办公生活板房 | D33: m² | E33: 人工 | F33: L01 | G33: 普通工 | H33: 工日 | I33: 0.12 | J33: =IFERROR(VLOOKUP(F33,工料机价格!$A$4:$F$45,6,FALSE()),0) -> 300 | K33: =I33*J33 -> 36 | L33: =IF(E33="人工",K33,0) -> 36 | M33: =IF(E33="材料",K33,0) -> 0 | N33: =IF(OR(E33="机械",E33="外委"),K33,0) -> 0 | O33: 安拆
A34: 6.2 | B34: SF06 | C34: 办公生活板房 | D34: m² | E34: 人工 | F34: L02 | G34: 技术工/带班 | H34: 工日 | I34: 0.02 | J34: =IFERROR(VLOOKUP(F34,工料机价格!$A$4:$F$45,6,FALSE()),0) -> 350 | K34: =I34*J34 -> 7 | L34: =IF(E34="人工",K34,0) -> 7 | M34: =IF(E34="材料",K34,0) -> 0 | N34: =IF(OR(E34="机械",E34="外委"),K34,0) -> 0 | O34: 水电
A35: 6.3 | B35: SF06 | C35: 办公生活板房 | D35: m² | E35: 材料 | F35: BRD | G35: 岩棉夹芯板 | H35: m² | I35: 2.2 | J35: =IFERROR(VLOOKUP(F35,工料机价格!$A$4:$F$45,6,FALSE()),0) -> 180 | K35: =I35*J35 -> 396 | L35: =IF(E35="人工",K35,0) -> 0 | M35: =IF(E35="材料",K35,0) -> 396 | N35: =IF(OR(E35="机械",E35="外委"),K35,0) -> 0 | O35: 墙屋展开
A36: 6.4 | B36: SF06 | C36: 办公生活板房 | D36: m² | E36: 材料 | F36: C20 | G36: C20商品混凝土 | H36: m³ | I36: 0.08 | J36: =IFERROR(VLOOKUP(F36,工料机价格!$A$4:$F$45,6,FALSE()),0) -> 345 | K36: =I36*J36 -> 27.6 | L36: =IF(E36="人工",K36,0) -> 0 | M36: =IF(E36="材料",K36,0) -> 27.6 | N36: =IF(OR(E36="机械",E36="外委"),K36,0) -> 0 | O36: 地坪
A37: 6.5 | B37: SF06 | C37: 办公生活板房 | D37: m² | E37: 机械 | F37: CRN | G37: 汽车吊25t台班 | H37: 台班 | I37: 0.004 | J37: =IFERROR(VLOOKUP(F37,工料机价格!$A$4:$F$45,6,FALSE()),0) -> 1772.95 | K37: =I37*J37 -> 7.0918 | L37: =IF(E37="人工",K37,0) -> 0 | M37: =IF(E37="材料",K37,0) -> 0 | N37: =IF(OR(E37="机械",E37="外委"),K37,0) -> 7.0918 | O37: 吊装
A38: 7 | B38: SF07 | C38: 污染土壤清挖及场内短驳 | D38: m³ | E38: 汇总 | K38: =SUM(K39:K41) -> 24.53829 | L38: =SUMIF(E39:E41,"人工",K39:K41) -> 3 | M38: =SUMIF(E39:E41,"材料",K39:K41) -> 0 | N38: =SUMIF(E39:E41,"机械",K39:K41)+SUMIF(E39:E41,"外委",K39:K41) -> 21.53829 | O38: 120 m³/台班开挖+场内约200 m，不采用可研50元/m³ | P38: =K38 -> 24.53829
A39: 7.1 | B39: SF07 | C39: 污染土壤清挖及场内短驳 | D39: m³ | E39: 机械 | F39: EXC | G39: 挖掘机1.0m³台班 | H39: 台班 | I39: 0.0083 | J39: =IFERROR(VLOOKUP(F39,工料机价格!$A$4:$F$45,6,FALSE()),0) -> 1773.3 | K39: =I39*J39 -> 14.71839 | L39: =IF(E39="人工",K39,0) -> 0 | M39: =IF(E39="材料",K39,0) -> 0 | N39: =IF(OR(E39="机械",E39="外委"),K39,0) -> 14.71839 | O39: 1/120
A40: 7.2 | B40: SF07 | C40: 污染土壤清挖及场内短驳 | D40: m³ | E40: 机械 | F40: DMP | G40: 自卸汽车15t台班 | H40: 台班 | I40: 0.006 | J40: =IFERROR(VLOOKUP(F40,工料机价格!$A$4:$F$45,6,FALSE()),0) -> 1136.65 | K40: =I40*J40 -> 6.8199 | L40: =IF(E40="人工",K40,0) -> 0 | M40: =IF(E40="材料",K40,0) -> 0 | N40: =IF(OR(E40="机械",E40="外委"),K40,0) -> 6.8199 | O40: 场内短驳
A41: 7.3 | B41: SF07 | C41: 污染土壤清挖及场内短驳 | D41: m³ | E41: 人工 | F41: L01 | G41: 普通工 | H41: 工日 | I41: 0.01 | J41: =IFERROR(VLOOKUP(F41,工料机价格!$A$4:$F$45,6,FALSE()),0) -> 300 | K41: =I41*J41 -> 3 | L41: =IF(E41="人工",K41,0) -> 3 | M41: =IF(E41="材料",K41,0) -> 0 | N41: =IF(OR(E41="机械",E41="外委"),K41,0) -> 0 | O41: 清底、防护
A42: 8 | B42: SF08 | C42: 筛分破碎 | D42: m³ | E42: 汇总 | K42: =SUM(K43:K46) -> 21.9063 | L42: =SUMIF(E43:E46,"人工",K43:K46) -> 2.4 | M42: =SUMIF(E43:E46,"材料",K43:K46) -> 0 | N42: =SUMIF(E43:E46,"机械",K43:K46)+SUMIF(E43:E46,"外委",K43:K46) -> 19.5063 | O42: 阿鲁斗至进窑粒径。主机用挖掘机，筛分斗另计。不采用可研60元/m³ | P42: =K42 -> 21.9063
A43: 8.1 | B43: SF08 | C43: 筛分破碎 | D43: m³ | E43: 机械 | F43: EXC | G43: 挖掘机1.0m³台班 | H43: 台班 | I43: 0.006 | J43: =IFERROR(VLOOKUP(F43,工料机价格!$A$4:$F$45,6,FALSE()),0) -> 1773.3 | K43: =I43*J43 -> 10.6398 | L43: =IF(E43="人工",K43,0) -> 0 | M43: =IF(E43="材料",K43,0) -> 0 | N43: =IF(OR(E43="机械",E43="外委"),K43,0) -> 10.6398 | O43: 上料主机
A44: 8.2 | B44: SF08 | C44: 筛分破碎 | D44: m³ | E44: 机械 | F44: ALU | G44: 阿鲁斗筛分台班 | H44: 台班 | I44: 0.006 | J44: =IFERROR(VLOOKUP(F44,工料机价格!$A$4:$F$45,6,FALSE()),0) -> 754.8 | K44: =I44*J44 -> 4.5288 | L44: =IF(E44="人工",K44,0) -> 0 | M44: =IF(E44="材料",K44,0) -> 0 | N44: =IF(OR(E44="机械",E44="外委"),K44,0) -> 4.5288 | O44: 与主机同台班
A45: 8.3 | B45: SF08 | C45: 筛分破碎 | D45: m³ | E45: 机械 | F45: LDR | G45: 装载机50型台班 | H45: 台班 | I45: 0.003 | J45: =IFERROR(VLOOKUP(F45,工料机价格!$A$4:$F$45,6,FALSE()),0) -> 1445.9 | K45: =I45*J45 -> 4.3377 | L45: =IF(E45="人工",K45,0) -> 0 | M45: =IF(E45="材料",K45,0) -> 0 | N45: =IF(OR(E45="机械",E45="外委"),K45,0) -> 4.3377 | O45: 堆料
A46: 8.4 | B46: SF08 | C46: 筛分破碎 | D46: m³ | E46: 人工 | F46: L01 | G46: 普通工 | H46: 工日 | I46: 0.008 | J46: =IFERROR(VLOOKUP(F46,工料机价格!$A$4:$F$45,6,FALSE()),0) -> 300 | K46: =I46*J46 -> 2.4 | L46: =IF(E46="人工",K46,0) -> 2.4 | M46: =IF(E46="材料",K46,0) -> 0 | N46: =IF(OR(E46="机械",E46="外委"),K46,0) -> 0 | O46: 捡大块
A47: 9 | B47: SF09 | C47: 砂卵石清洗 | D47: m³ | E47: 汇总 | K47: =SUM(K48:K51) -> 17.2428 | L47: =SUMIF(E48:E51,"人工",K48:K51) -> 6 | M47: =SUMIF(E48:E51,"材料",K48:K51) -> 0.44 | N47: =SUMIF(E48:E51,"机械",K48:K51)+SUMIF(E48:E51,"外委",K48:K51) -> 10.8028 | O47: 高压冲洗+药剂，不含废水处置。不采用可研80元/m³ | P47: =K47 -> 17.2428
A48: 9.1 | B48: SF09 | C48: 砂卵石清洗 | D48: m³ | E48: 机械 | F48: WSHM | G48: 高压冲洗台班 | H48: 台班 | I48: 0.008 | J48: =IFERROR(VLOOKUP(F48,工料机价格!$A$4:$F$45,6,FALSE()),0) -> 627.4 | K48: =I48*J48 -> 5.0192 | L48: =IF(E48="人工",K48,0) -> 0 | M48: =IF(E48="材料",K48,0) -> 0 | N48: =IF(OR(E48="机械",E48="外委"),K48,0) -> 5.0192 | O48: 冲洗
A49: 9.2 | B49: SF09 | C49: 砂卵石清洗 | D49: m³ | E49: 机械 | F49: LDR | G49: 装载机50型台班 | H49: 台班 | I49: 0.004 | J49: =IFERROR(VLOOKUP(F49,工料机价格!$A$4:$F$45,6,FALSE()),0) -> 1445.9 | K49: =I49*J49 -> 5.7836 | L49: =IF(E49="人工",K49,0) -> 0 | M49: =IF(E49="材料",K49,0) -> 0 | N49: =IF(OR(E49="机械",E49="外委"),K49,0) -> 5.7836 | O49: 上料
A50: 9.3 | B50: SF09 | C50: 砂卵石清洗 | D50: m³ | E50: 材料 | F50: PAC | G50: 聚合氯化铝PAC | H50: t | I50: 0.0004 | J50: =IFERROR(VLOOKUP(F50,工料机价格!$A$4:$F$45,6,FALSE()),0) -> 1100 | K50: =I50*J50 -> 0.44 | L50: =IF(E50="人工",K50,0) -> 0 | M50: =IF(E50="材料",K50,0) -> 0.44 | N50: =IF(OR(E50="机械",E50="外委"),K50,0) -> 0 | O50: 助沉
A51: 9.4 | B51: SF09 | C51: 砂卵石清洗 | D51: m³ | E51: 人工 | F51: L01 | G51: 普通工 | H51: 工日 | I51: 0.02 | J51: =IFERROR(VLOOKUP(F51,工料机价格!$A$4:$F$45,6,FALSE()),0) -> 300 | K51: =I51*J51 -> 6 | L51: =IF(E51="人工",K51,0) -> 6 | M51: =IF(E51="材料",K51,0) -> 0 | N51: =IF(OR(E51="机械",E51="外委"),K51,0) -> 0 | O51: 冲洗、翻堆
A52: 10 | B52: SF10 | C52: 卵石清洗废水预处理 | D52: m³ | E52: 汇总 | K52: =SUM(K53:K56) -> 4.787 | L52: =SUMIF(E53:E56,"人工",K53:K56) -> 3 | M52: =SUMIF(E53:E56,"材料",K53:K56) -> 0.186 | N52: =SUMIF(E53:E56,"机械",K53:K56)+SUMIF(E53:E56,"外委",K53:K56) -> 1.601 | O52: 混凝沉淀运行，不含设施建安 | P52: =K52 -> 4.787
A53: 10.1 | B53: SF10 | C53: 卵石清洗废水预处理 | D53: m³ | E53: 材料 | F53: PAC | G53: 聚合氯化铝PAC | H53: t | I53: 0.00015 | J53: =IFERROR(VLOOKUP(F53,工料机价格!$A$4:$F$45,6,FALSE()),0) -> 1100 | K53: =I53*J53 -> 0.165 | L53: =IF(E53="人工",K53,0) -> 0 | M53: =IF(E53="材料",K53,0) -> 0.165 | N53: =IF(OR(E53="机械",E53="外委"),K53,0) -> 0 | O53: 混凝
A54: 10.2 | B54: SF10 | C54: 卵石清洗废水预处理 | D54: m³ | E54: 材料 | F54: PAM | G54: 聚丙烯酰胺PAM | H54: t | I54: 3e-06 | J54: =IFERROR(VLOOKUP(F54,工料机价格!$A$4:$F$45,6,FALSE()),0) -> 7000 | K54: =I54*J54 -> 0.021 | L54: =IF(E54="人工",K54,0) -> 0 | M54: =IF(E54="材料",K54,0) -> 0.021 | N54: =IF(OR(E54="机械",E54="外委"),K54,0) -> 0 | O54: 助凝
A55: 10.3 | B55: SF10 | C55: 卵石清洗废水预处理 | D55: m³ | E55: 机械 | F55: WP | G55: 潜水泵7.5kW台班 | H55: 台班 | I55: 0.02 | J55: =IFERROR(VLOOKUP(F55,工料机价格!$A$4:$F$45,6,FALSE()),0) -> 80.05 | K55: =I55*J55 -> 1.601 | L55: =IF(E55="人工",K55,0) -> 0 | M55: =IF(E55="材料",K55,0) -> 0 | N55: =IF(OR(E55="机械",E55="外委"),K55,0) -> 1.601 | O55: 提升
A56: 10.4 | B56: SF10 | C56: 卵石清洗废水预处理 | D56: m³ | E56: 人工 | F56: L01 | G56: 普通工 | H56: 工日 | I56: 0.01 | J56: =IFERROR(VLOOKUP(F56,工料机价格!$A$4:$F$45,6,FALSE()),0) -> 300 | K56: =I56*J56 -> 3 | L56: =IF(E56="人工",K56,0) -> 3 | M56: =IF(E56="材料",K56,0) -> 0 | N56: =IF(OR(E56="机械",E56="外委"),K56,0) -> 0 | O56: 加药、排泥
A57: 11 | B57: SF11 | C57: 预处理后废水外运 | D57: m³ | E57: 汇总 | K57: =SUM(K58:K59) -> 46.966 | L57: =SUMIF(E58:E59,"人工",K58:K59) -> 1.5 | M57: =SUMIF(E58:E59,"材料",K58:K59) -> 0 | N57: =SUMIF(E58:E59,"机械",K58:K59)+SUMIF(E58:E59,"外委",K58:K59) -> 45.466 | O57: 10 m³/车，场外短运 | P57: =K57 -> 46.966
A58: 11.1 | B58: SF11 | C58: 预处理后废水外运 | D58: m³ | E58: 机械 | F58: DMP | G58: 自卸汽车15t台班 | H58: 台班 | I58: 0.04 | J58: =IFERROR(VLOOKUP(F58,工料机价格!$A$4:$F$45,6,FALSE()),0) -> 1136.65 | K58: =I58*J58 -> 45.466 | L58: =IF(E58="人工",K58,0) -> 0 | M58: =IF(E58="材料",K58,0) -> 0 | N58: =IF(OR(E58="机械",E58="外委"),K58,0) -> 45.466 | O58: 罐车近似
A59: 11.2 | B59: SF11 | C59: 预处理后废水外运 | D59: m³ | E59: 人工 | F59: L01 | G59: 普通工 | H59: 工日 | I59: 0.005 | J59: =IFERROR(VLOOKUP(F59,工料机价格!$A$4:$F$45,6,FALSE()),0) -> 300 | K59: =I59*J59 -> 1.5 | L59: =IF(E59="人工",K59,0) -> 1.5 | M59: =IF(E59="材料",K59,0) -> 0 | N59: =IF(OR(E59="机械",E59="外委"),K59,0) -> 0 | O59: 装卸
A60: 12 | B60: SF12 | C60: 工业污水厂接收 | D60: m³ | E60: 汇总 | K60: =SUM(K61) -> 75 | L60: =SUMIF(E61,"人工",K61) -> 0 | M60: =SUMIF(E61,"材料",K61) -> 0 | N60: =SUMIF(E61,"机械",K61)+SUMIF(E61,"外委",K61) -> 75 | O60: 外委接收，无什邡合同，用成本库75元/m³ | P60: =K60 -> 75
A61: 12.1 | B61: SF12 | C61: 工业污水厂接收 | D61: m³ | E61: 外委 | F61: WWD | G61: 工业污水厂接收 | H61: m³ | I61: 1 | J61: =IFERROR(VLOOKUP(F61,工料机价格!$A$4:$F$45,6,FALSE()),0) -> 75 | K61: =I61*J61 -> 75 | L61: =IF(E61="人工",K61,0) -> 0 | M61: =IF(E61="材料",K61,0) -> 0 | N61: =IF(OR(E61="机械",E61="外委"),K61,0) -> 75 | O61: 不拆人材机
A62: 13 | B62: SF13 | C62: 水泥窑协同处置 | D62: t | E62: 汇总 | K62: =SUM(K63) -> 190 | L62: =SUMIF(E63,"人工",K63) -> 0 | M62: =SUMIF(E63,"材料",K63) -> 0 | N62: =SUMIF(E63,"机械",K63)+SUMIF(E63,"外委",K63) -> 190 | O62: 不含运190元/t。不采用可研1100元/m³ | P62: =K62 -> 190
A63: 13.1 | B63: SF13 | C63: 水泥窑协同处置 | D63: t | E63: 外委 | F63: KILN | G63: 水泥窑协同处置 | H63: t | I63: 1 | J63: =IFERROR(VLOOKUP(F63,工料机价格!$A$4:$F$45,6,FALSE()),0) -> 190 | K63: =I63*J63 -> 190 | L63: =IF(E63="人工",K63,0) -> 0 | M63: =IF(E63="材料",K63,0) -> 0 | N63: =IF(OR(E63="机械",E63="外委"),K63,0) -> 190 | O63: 用户确认
A64: 14 | B64: SF14 | C64: 水泥窑密闭运输 | D64: t | E64: 汇总 | K64: =SUM(K65:K66) -> 44 | L64: =SUMIF(E65:E66,"人工",K65:K66) -> 0 | M64: =SUMIF(E65:E66,"材料",K65:K66) -> 44 | N64: =SUMIF(E65:E66,"机械",K65:K66)+SUMIF(E65:E66,"外委",K65:K66) -> 0 | O64: 0.80元/t·km×运距+路桥过磅。不采用可研150元/m³ | P64: =K64 -> 44
A65: 14.1 | B65: SF14 | C65: 水泥窑密闭运输 | D65: t | E65: 材料 | F65: TRK | G65: 密闭运输单价 | H65: t·km | I65: =工程量计算!C10 -> 40 | J65: =IFERROR(VLOOKUP(F65,工料机价格!$A$4:$F$45,6,FALSE()),0) -> 0.8 | K65: =I65*J65 -> 32 | L65: =IF(E65="人工",K65,0) -> 0 | M65: =IF(E65="材料",K65,0) -> 32 | N65: =IF(OR(E65="机械",E65="外委"),K65,0) -> 0 | O65: 运距，黄底在工程量表
A66: 14.2 | B66: SF14 | C66: 水泥窑密闭运输 | D66: t | E66: 材料 | F66: TOLL | G66: 高速路桥及过磅 | H66: t | I66: 1 | J66: =IFERROR(VLOOKUP(F66,工料机价格!$A$4:$F$45,6,FALSE()),0) -> 12 | K66: =I66*J66 -> 12 | L66: =IF(E66="人工",K66,0) -> 0 | M66: =IF(E66="材料",K66,0) -> 12 | N66: =IF(OR(E66="机械",E66="外委"),K66,0) -> 0 | O66: 每吨一次
A67: 15 | B67: SF15 | C67: 含汞污染土壤安全处置 | D67: m³ | E67: 汇总 | K67: =SUM(K68) -> 2800 | L67: =SUMIF(E68,"人工",K68) -> 0 | M67: =SUMIF(E68,"材料",K68) -> 0 | N67: =SUMIF(E68,"机械",K68)+SUMIF(E68,"外委",K68) -> 2800 | O67: 2800元/m³，不含运。不采用可研5000元/m³ | P67: =K67 -> 2800
A68: 15.1 | B68: SF15 | C68: 含汞污染土壤安全处置 | D68: m³ | E68: 外委 | F68: HG | G68: 含汞污染土壤安全处置 | H68: m³ | I68: 1 | J68: =IFERROR(VLOOKUP(F68,工料机价格!$A$4:$F$45,6,FALSE()),0) -> 2800 | K68: =I68*J68 -> 2800 | L68: =IF(E68="人工",K68,0) -> 0 | M68: =IF(E68="材料",K68,0) -> 0 | N68: =IF(OR(E68="机械",E68="外委"),K68,0) -> 2800 | O68: 川发改价格〔2011〕1776号口径
A69: 16 | B69: SF16 | C69: 含汞密闭运输 | D69: t | E69: 汇总 | K69: =SUM(K70:K71) -> 76 | L69: =SUMIF(E70:E71,"人工",K70:K71) -> 0 | M69: =SUMIF(E70:E71,"材料",K70:K71) -> 76 | N69: =SUMIF(E70:E71,"机械",K70:K71)+SUMIF(E70:E71,"外委",K70:K71) -> 0 | O69: 0.80元/t·km×含汞运距+路桥。不采用可研100元/m³ | P69: =K69 -> 76
A70: 16.1 | B70: SF16 | C70: 含汞密闭运输 | D70: t | E70: 材料 | F70: TRK | G70: 密闭运输单价 | H70: t·km | I70: =工程量计算!C11 -> 80 | J70: =IFERROR(VLOOKUP(F70,工料机价格!$A$4:$F$45,6,FALSE()),0) -> 0.8 | K70: =I70*J70 -> 64 | L70: =IF(E70="人工",K70,0) -> 0 | M70: =IF(E70="材料",K70,0) -> 64 | N70: =IF(OR(E70="机械",E70="外委"),K70,0) -> 0 | O70: 含汞运距
A71: 16.2 | B71: SF16 | C71: 含汞密闭运输 | D71: t | E71: 材料 | F71: TOLL | G71: 高速路桥及过磅 | H71: t | I71: 1 | J71: =IFERROR(VLOOKUP(F71,工料机价格!$A$4:$F$45,6,FALSE()),0) -> 12 | K71: =I71*J71 -> 12 | L71: =IF(E71="人工",K71,0) -> 0 | M71: =IF(E71="材料",K71,0) -> 12 | N71: =IF(OR(E71="机械",E71="外委"),K71,0) -> 0 | O71: 每吨一次
A72: 17 | B72: SF17 | C72: 清洗后砂卵石回填 | D72: m³ | E72: 汇总 | K72: =SUM(K73:K76) -> 13.1302 | L72: =SUMIF(E73:E76,"人工",K73:K76) -> 2.4 | M72: =SUMIF(E73:E76,"材料",K73:K76) -> 0 | N72: =SUMIF(E73:E76,"机械",K73:K76)+SUMIF(E73:E76,"外委",K73:K76) -> 10.7302 | O72: 场内短驳+分层碾压。不采用可研50元/m³ | P72: =K72 -> 13.1302
A73: 17.1 | B73: SF17 | C73: 清洗后砂卵石回填 | D73: m³ | E73: 机械 | F73: DMP | G73: 自卸汽车15t台班 | H73: 台班 | I73: 0.004 | J73: =IFERROR(VLOOKUP(F73,工料机价格!$A$4:$F$45,6,FALSE()),0) -> 1136.65 | K73: =I73*J73 -> 4.5466 | L73: =IF(E73="人工",K73,0) -> 0 | M73: =IF(E73="材料",K73,0) -> 0 | N73: =IF(OR(E73="机械",E73="外委"),K73,0) -> 4.5466 | O73: 场内短驳
A74: 17.2 | B74: SF17 | C74: 清洗后砂卵石回填 | D74: m³ | E74: 机械 | F74: EXC | G74: 挖掘机1.0m³台班 | H74: 台班 | I74: 0.002 | J74: =IFERROR(VLOOKUP(F74,工料机价格!$A$4:$F$45,6,FALSE()),0) -> 1773.3 | K74: =I74*J74 -> 3.5466 | L74: =IF(E74="人工",K74,0) -> 0 | M74: =IF(E74="材料",K74,0) -> 0 | N74: =IF(OR(E74="机械",E74="外委"),K74,0) -> 3.5466 | O74: 摊铺
A75: 17.3 | B75: SF17 | C75: 清洗后砂卵石回填 | D75: m³ | E75: 机械 | F75: RL | G75: 压路机台班 | H75: 台班 | I75: 0.0025 | J75: =IFERROR(VLOOKUP(F75,工料机价格!$A$4:$F$45,6,FALSE()),0) -> 1054.8 | K75: =I75*J75 -> 2.637 | L75: =IF(E75="人工",K75,0) -> 0 | M75: =IF(E75="材料",K75,0) -> 0 | N75: =IF(OR(E75="机械",E75="外委"),K75,0) -> 2.637 | O75: 碾压
A76: 17.4 | B76: SF17 | C76: 清洗后砂卵石回填 | D76: m³ | E76: 人工 | F76: L01 | G76: 普通工 | H76: 工日 | I76: 0.008 | J76: =IFERROR(VLOOKUP(F76,工料机价格!$A$4:$F$45,6,FALSE()),0) -> 300 | K76: =I76*J76 -> 2.4 | L76: =IF(E76="人工",K76,0) -> 2.4 | M76: =IF(E76="材料",K76,0) -> 0 | N76: =IF(OR(E76="机械",E76="外委"),K76,0) -> 0 | O76: 清底
A77: 18 | B77: SF18 | C77: 外购清洁土 | D77: m³ | E77: 汇总 | K77: =SUM(K78) -> 80 | L77: =SUMIF(E78,"人工",K78) -> 0 | M77: =SUMIF(E78,"材料",K78) -> 0 | N77: =SUMIF(E78,"机械",K78)+SUMIF(E78,"外委",K78) -> 80 | O77: 什邡周边到场80元/m³。不采用可研120元/m³，不套雅安45元/m³ | P77: =K77 -> 80
A78: 18.1 | B78: SF18 | C78: 外购清洁土 | D78: m³ | E78: 外委 | F78: SOIL | G78: 外购清洁土 | H78: m³ | I78: 1 | J78: =IFERROR(VLOOKUP(F78,工料机价格!$A$4:$F$45,6,FALSE()),0) -> 80 | K78: =I78*J78 -> 80 | L78: =IF(E78="人工",K78,0) -> 0 | M78: =IF(E78="材料",K78,0) -> 0 | N78: =IF(OR(E78="机械",E78="外委"),K78,0) -> 80 | O78: 供方挖装运
A79: 19 | B79: SF19 | C79: 清洁土分层回填压实 | D79: m³ | E79: 汇总 | K79: =SUM(K80:K83) -> 11.39355 | L79: =SUMIF(E80:E83,"人工",K80:K83) -> 1.8 | M79: =SUMIF(E80:E83,"材料",K80:K83) -> 0 | N79: =SUMIF(E80:E83,"机械",K80:K83)+SUMIF(E80:E83,"外委",K80:K83) -> 9.59355 | O79: 分层不大于300 mm。购置与压实拆开 | P79: =K79 -> 11.39355
A80: 19.1 | B80: SF19 | C80: 清洁土分层回填压实 | D80: m³ | E80: 机械 | F80: DMP | G80: 自卸汽车15t台班 | H80: 台班 | I80: 0.003 | J80: =IFERROR(VLOOKUP(F80,工料机价格!$A$4:$F$45,6,FALSE()),0) -> 1136.65 | K80: =I80*J80 -> 3.40995 | L80: =IF(E80="人工",K80,0) -> 0 | M80: =IF(E80="材料",K80,0) -> 0 | N80: =IF(OR(E80="机械",E80="外委"),K80,0) -> 3.40995 | O80: 场内倒运
A81: 19.2 | B81: SF19 | C81: 清洁土分层回填压实 | D81: m³ | E81: 机械 | F81: EXC | G81: 挖掘机1.0m³台班 | H81: 台班 | I81: 0.002 | J81: =IFERROR(VLOOKUP(F81,工料机价格!$A$4:$F$45,6,FALSE()),0) -> 1773.3 | K81: =I81*J81 -> 3.5466 | L81: =IF(E81="人工",K81,0) -> 0 | M81: =IF(E81="材料",K81,0) -> 0 | N81: =IF(OR(E81="机械",E81="外委"),K81,0) -> 3.5466 | O81: 摊铺
A82: 19.3 | B82: SF19 | C82: 清洁土分层回填压实 | D82: m³ | E82: 机械 | F82: RL | G82: 压路机台班 | H82: 台班 | I82: 0.0025 | J82: =IFERROR(VLOOKUP(F82,工料机价格!$A$4:$F$45,6,FALSE()),0) -> 1054.8 | K82: =I82*J82 -> 2.637 | L82: =IF(E82="人工",K82,0) -> 0 | M82: =IF(E82="材料",K82,0) -> 0 | N82: =IF(OR(E82="机械",E82="外委"),K82,0) -> 2.637 | O82: 碾压
A83: 19.4 | B83: SF19 | C83: 清洁土分层回填压实 | D83: m³ | E83: 人工 | F83: L01 | G83: 普通工 | H83: 工日 | I83: 0.006 | J83: =IFERROR(VLOOKUP(F83,工料机价格!$A$4:$F$45,6,FALSE()),0) -> 300 | K83: =I83*J83 -> 1.8 | L83: =IF(E83="人工",K83,0) -> 1.8 | M83: =IF(E83="材料",K83,0) -> 0 | N83: =IF(OR(E83="机械",E83="外委"),K83,0) -> 0 | O83: 整平
A84: 20 | B84: SF20 | C84: 地下水监测井成井 | D84: 口 | E84: 汇总 | K84: =SUM(K85:K90) -> 6969.04 | L84: =SUMIF(E85:E90,"人工",K85:K90) -> 1250 | M84: =SUMIF(E85:E90,"材料",K85:K90) -> 1900.4 | N84: =SUMIF(E85:E90,"机械",K85:K90)+SUMIF(E85:E90,"外委",K85:K90) -> 3818.64 | O84: 深20 m，钻机成井。不是降水井。不采用可研500元/m+2000元/口 | P84: =K84 -> 6969.04
A85: 20.1 | B85: SF20 | C85: 地下水监测井成井 | D85: 口 | E85: 机械 | F85: RIG | G85: 成井钻机台班 | H85: 台班 | I85: 1.2 | J85: =IFERROR(VLOOKUP(F85,工料机价格!$A$4:$F$45,6,FALSE()),0) -> 3182.2 | K85: =I85*J85 -> 3818.64 | L85: =IF(E85="人工",K85,0) -> 0 | M85: =IF(E85="材料",K85,0) -> 0 | N85: =IF(OR(E85="机械",E85="外委"),K85,0) -> 3818.64 | O85: 20 m卵石层
A86: 20.2 | B86: SF20 | C86: 地下水监测井成井 | D86: 口 | E86: 材料 | F86: PIPE | G86: 监测井管 | H86: m | I86: 20 | J86: =IFERROR(VLOOKUP(F86,工料机价格!$A$4:$F$45,6,FALSE()),0) -> 85 | K86: =I86*J86 -> 1700 | L86: =IF(E86="人工",K86,0) -> 0 | M86: =IF(E86="材料",K86,0) -> 1700 | N86: =IF(OR(E86="机械",E86="外委"),K86,0) -> 0 | O86: 井深
A87: 20.3 | B87: SF20 | C87: 地下水监测井成井 | D87: 口 | E87: 材料 | F87: AGG | G87: 级配碎石 | H87: m³ | I87: 0.8 | J87: =IFERROR(VLOOKUP(F87,工料机价格!$A$4:$F$45,6,FALSE()),0) -> 78 | K87: =I87*J87 -> 62.4 | L87: =IF(E87="人工",K87,0) -> 0 | M87: =IF(E87="材料",K87,0) -> 62.4 | N87: =IF(OR(E87="机械",E87="外委"),K87,0) -> 0 | O87: 滤料
A88: 20.4 | B88: SF20 | C88: 地下水监测井成井 | D88: 口 | E88: 材料 | F88: C20 | G88: C20商品混凝土 | H88: m³ | I88: 0.4 | J88: =IFERROR(VLOOKUP(F88,工料机价格!$A$4:$F$45,6,FALSE()),0) -> 345 | K88: =I88*J88 -> 138 | L88: =IF(E88="人工",K88,0) -> 0 | M88: =IF(E88="材料",K88,0) -> 138 | N88: =IF(OR(E88="机械",E88="外委"),K88,0) -> 0 | O88: 井台
A89: 20.5 | B89: SF20 | C89: 地下水监测井成井 | D89: 口 | E89: 人工 | F89: L01 | G89: 普通工 | H89: 工日 | I89: 3 | J89: =IFERROR(VLOOKUP(F89,工料机价格!$A$4:$F$45,6,FALSE()),0) -> 300 | K89: =I89*J89 -> 900 | L89: =IF(E89="人工",K89,0) -> 900 | M89: =IF(E89="材料",K89,0) -> 0 | N89: =IF(OR(E89="机械",E89="外委"),K89,0) -> 0 | O89: 下管、洗井
A90: 20.6 | B90: SF20 | C90: 地下水监测井成井 | D90: 口 | E90: 人工 | F90: L02 | G90: 技术工/带班 | H90: 工日 | I90: 1 | J90: =IFERROR(VLOOKUP(F90,工料机价格!$A$4:$F$45,6,FALSE()),0) -> 350 | K90: =I90*J90 -> 350 | L90: =IF(E90="人工",K90,0) -> 350 | M90: =IF(E90="材料",K90,0) -> 0 | N90: =IF(OR(E90="机械",E90="外委"),K90,0) -> 0 | O90: 成井记录
A91: 21 | B91: SF21 | C91: 地下水长期监测 | D91: 样 | E91: 汇总 | K91: =SUM(K92) -> 1200 | L91: =SUMIF(E92,"人工",K92) -> 0 | M91: =SUMIF(E92,"材料",K92) -> 0 | N91: =SUMIF(E92,"机械",K92)+SUMIF(E92,"外委",K92) -> 1200 | O91: 外委，指标为铅 | P91: =K91 -> 1200
A92: 21.1 | B92: SF21 | C92: 地下水长期监测 | D92: 样 | E92: 外委 | F92: GW | G92: 地下水监测外委 | H92: 样 | I92: 1 | J92: =IFERROR(VLOOKUP(F92,工料机价格!$A$4:$F$45,6,FALSE()),0) -> 1200 | K92: =I92*J92 -> 1200 | L92: =IF(E92="人工",K92,0) -> 0 | M92: =IF(E92="材料",K92,0) -> 0 | N92: =IF(OR(E92="机械",E92="外委"),K92,0) -> 1200 | O92: 不拆人材机
A93: 22 | B93: SF22 | C93: 防尘网铺设 | D93: m² | E93: 汇总 | K93: =SUM(K94:K95) -> 3.825 | L93: =SUMIF(E94:E95,"人工",K94:K95) -> 1.2 | M93: =SUMIF(E94:E95,"材料",K94:K95) -> 2.625 | N93: =SUMIF(E94:E95,"机械",K94:K95)+SUMIF(E94:E95,"外委",K94:K95) -> 0 | O93: 材料+铺设。不采用可研10元/m² | P93: =K93 -> 3.825
A94: 22.1 | B94: SF22 | C94: 防尘网铺设 | D94: m² | E94: 人工 | F94: L01 | G94: 普通工 | H94: 工日 | I94: 0.004 | J94: =IFERROR(VLOOKUP(F94,工料机价格!$A$4:$F$45,6,FALSE()),0) -> 300 | K94: =I94*J94 -> 1.2 | L94: =IF(E94="人工",K94,0) -> 1.2 | M94: =IF(E94="材料",K94,0) -> 0 | N94: =IF(OR(E94="机械",E94="外委"),K94,0) -> 0 | O94: 铺设压边
A95: 22.2 | B95: SF22 | C95: 防尘网铺设 | D95: m² | E95: 材料 | F95: NET | G95: 防尘网 | H95: m² | I95: 1.05 | J95: =IFERROR(VLOOKUP(F95,工料机价格!$A$4:$F$45,6,FALSE()),0) -> 2.5 | K95: =I95*J95 -> 2.625 | L95: =IF(E95="人工",K95,0) -> 0 | M95: =IF(E95="材料",K95,0) -> 2.625 | N95: =IF(OR(E95="机械",E95="外委"),K95,0) -> 0 | O95: 含损耗
A96: 23 | B96: SF23 | C96: 地表导排沟 | D96: m | E96: 汇总 | K96: =SUM(K97:K101) -> 85.1199 | L96: =SUMIF(E97:E101,"人工",K97:K101) -> 30 | M96: =SUMIF(E97:E101,"材料",K97:K101) -> 49.8 | N96: =SUMIF(E97:E101,"机械",K97:K101)+SUMIF(E97:E101,"外委",K97:K101) -> 5.3199 | O96: 0.3×0.3 m砖沟。不采用可研500元/m | P96: =K96 -> 85.1199
A97: 23.1 | B97: SF23 | C97: 地表导排沟 | D97: m | E97: 人工 | F97: L01 | G97: 普通工 | H97: 工日 | I97: 0.1 | J97: =IFERROR(VLOOKUP(F97,工料机价格!$A$4:$F$45,6,FALSE()),0) -> 300 | K97: =I97*J97 -> 30 | L97: =IF(E97="人工",K97,0) -> 30 | M97: =IF(E97="材料",K97,0) -> 0 | N97: =IF(OR(E97="机械",E97="外委"),K97,0) -> 0 | O97: 砌筑
A98: 23.2 | B98: SF23 | C98: 地表导排沟 | D98: m | E98: 材料 | F98: BRK | G98: 页岩配砖 | H98: 千块 | I98: 0.07 | J98: =IFERROR(VLOOKUP(F98,工料机价格!$A$4:$F$45,6,FALSE()),0) -> 330 | K98: =I98*J98 -> 23.1 | L98: =IF(E98="人工",K98,0) -> 0 | M98: =IF(E98="材料",K98,0) -> 23.1 | N98: =IF(OR(E98="机械",E98="外委"),K98,0) -> 0 | O98: 沟壁
A99: 23.3 | B99: SF23 | C99: 地表导排沟 | D99: m | E99: 材料 | F99: MOR | G99: 砌筑砂浆M10 | H99: t | I99: 0.06 | J99: =IFERROR(VLOOKUP(F99,工料机价格!$A$4:$F$45,6,FALSE()),0) -> 215 | K99: =I99*J99 -> 12.9 | L99: =IF(E99="人工",K99,0) -> 0 | M99: =IF(E99="材料",K99,0) -> 12.9 | N99: =IF(OR(E99="机械",E99="外委"),K99,0) -> 0 | O99: 砌筑
A100: 23.4 | B100: SF23 | C100: 地表导排沟 | D100: m | E100: 材料 | F100: C20 | G100: C20商品混凝土 | H100: m³ | I100: 0.04 | J100: =IFERROR(VLOOKUP(F100,工料机价格!$A$4:$F$45,6,FALSE()),0) -> 345 | K100: =I100*J100 -> 13.8 | L100: =IF(E100="人工",K100,0) -> 0 | M100: =IF(E100="材料",K100,0) -> 13.8 | N100: =IF(OR(E100="机械",E100="外委"),K100,0) -> 0 | O100: 沟底
...

Sheet 工料机价格
A1: 基础资源单价（F列黄底蓝字）。台班费用折旧+柴油+人工公式计算，不直接填别的项目包干价，也不引用投资估算单价。
A2: 柴油用乐山2026年7月信息价6.37元/L（成本库「柴油-综合-元-L」）。德阳同期信息价未入库，台班公式与旺平模版一致。管理费、利润、税金不在本表。
A3: 编码 | B3: 类别 | C3: 名称 | D3: 规格/计算式 | E3: 单位 | F3: 不含税单价（元） | G3: 来源 | H3: 备注
A4: DIE | B4: 材料 | C4: 0号柴油 | D4: 乐山信息价 | E4: L | F4: 6.37 | G4: 柴油-综合-元-L | H4: 乐山2026年7月不含税。德阳同期未入库
A5: L01 | B5: 人工 | C5: 普通工 | D5: 清底砌筑铺装巡井 | E5: 工日 | F5: 300 | G5: 普通工-太化建安-工日 | H5: 成本库
A6: L02 | B6: 人工 | C6: 技术工/带班 | D6: 测量焊接指挥 | E6: 工日 | F6: 350 | G6: 技工（大工/师傅）日工资 | H6: 成本库
A7: EXC | B7: 机械 | C7: 挖掘机1.0m³台班 | D7: 折旧900+柴油×90L+司机 | E7: 台班 | F7: =900+F4*90+F5 -> 1773.3 | G7: 台班公式 | H7: 油耗90 L/台班。不采用可研50元/m³包干
A8: LDR | B8: 机械 | C8: 装载机50型台班 | D8: 折旧700+柴油×70L+司机 | E8: 台班 | F8: =700+F4*70+F5 -> 1445.9 | G8: 台班公式 | H8: 油耗70 L/台班
A9: DMP | B9: 机械 | C9: 自卸汽车15t台班 | D9: 折旧550+柴油×45L+司机 | E9: 台班 | F9: =550+F4*45+F5 -> 1136.65 | G9: 台班公式 | H9: 场内倒运，不用于长途
A10: RL | B10: 机械 | C10: 压路机台班 | D10: 折旧500+柴油×40L+司机 | E10: 台班 | F10: =500+F4*40+F5 -> 1054.8 | G10: 台班公式 | H10: 油耗40 L/台班
A11: CRN | B11: 机械 | C11: 汽车吊25t台班 | D11: 折旧1200+柴油×35L+技工 | E11: 台班 | F11: =1200+F4*35+F6 -> 1772.95 | G11: 台班公式 | H11: 油耗35 L/台班
A12: ALU | B12: 机械 | C12: 阿鲁斗筛分台班 | D12: 折旧500+柴油×40L | E12: 台班 | F12: =500+F4*40 -> 754.8 | G12: 筛分设备-ALLU斗-台班对照 | H12: 主机折旧另计在挖掘机。本条只计筛分斗，不采用可研60元/m³
A13: WP | B13: 机械 | C13: 潜水泵7.5kW台班 | D13: 折旧40+电0.89×7.5×6h | E13: 台班 | F13: =40+0.89*7.5*6 -> 80.05 | G13: 台班公式 | H13: 电价0.89元/kWh，与旺平模版同口径
A14: SPR | B14: 机械 | C14: 洒水车台班 | D14: 折旧350+柴油×25L+司机 | E14: 台班 | F14: =350+F4*25+F5 -> 809.25 | G14: 台班公式 | H14: 降尘，不用渣土车代替
A15: WSHM | B15: 机械 | C15: 高压冲洗台班 | D15: 折旧200+柴油×20L+司机 | E15: 台班 | F15: =200+F4*20+F5 -> 627.4 | G15: 台班公式 | H15: 卵石冲洗主机。不采用可研80元/m³包干
A16: TRP | B16: 机械 | C16: 密闭渣土长途车次 | D16: 折旧400+往返油耗+司机 | E16: 车次 | F16: =400+F4*工程量计算!C10*2*工程量计算!C13+F5 -> 863.072 | G16: 车次公式 | H16: 实载12 t。运距取水泥窑运距，含汞另在清单按比例调整
A17: C20 | B17: 材料 | C17: C20商品混凝土 | D17: 泵送到场 | E17: m³ | F17: 345 | G17: 旺平-c20商品混凝土-元-m3 | H17: 库内C30市场均价365减20。不是信息价直接条目
A18: HDPE | B18: 材料 | C18: HDPE防渗膜1.5mm | D18: 双光面 | E18: m² | F18: 12 | G18: hdpe防渗膜-1-5mm双光面 | H18: 成本库。可研写2.0 mm，膜厚差在备注，不按可研300元/m²
A19: GT | B19: 材料 | C19: 土工布400g | D19: 非织造 | E19: m² | F19: 5 | G19: 非织造土工布-400g | H19: 成本库。可研写600 g，克重差在备注
A20: BRK | B20: 材料 | C20: 页岩配砖 | D20: 200×95×53 | E20: 千块 | F20: 330 | G20: 页岩配砖-200×95×53 | H20: 重庆2026年6月信息价
A21: MOR | B21: 材料 | C21: 砌筑砂浆M10 | D21: 预拌 | E21: t | F21: 215 | G21: 砌筑砂浆 | H21: 成本库，与旺平模版同价
A22: AGG | B22: 材料 | C22: 级配碎石 | D22: 便道基层到场 | E22: m³ | F22: 78 | G22: 估价 | H22: 库内无什邡碎石到场价，沿用旺平模版78元/m³
A23: CSP | B23: 材料 | C23: 彩钢板 | D23: 0.5 mm含檩条 | E23: m² | F23: 32 | G23: 估价 | H23: 围挡材料，与旺平模版同口径
A24: NET | B24: 材料 | C24: 防尘网 | D24: 6针，只计材料 | E24: m² | F24: 2.5 | G24: 估价 | H24: 不含铺设人工。不采用可研10元/m²综合价
A25: BRD | B25: 材料 | C25: 岩棉夹芯板 | D25: 活动房墙屋展开面积 | E25: m² | F25: 180 | G25: 由岩棉夹芯板活动房拆出 | H25: 不含地面和人工。不采用可研600元/m²买断
A26: PIPE | B26: 材料 | C26: 监测井管 | D26: 含滤水管、滤料 | E26: m | F26: 85 | G26: 估价 | H26: 库内无井管价，与旺平模版同口径。监测井不是降水井
A27: PAC | B27: 材料 | C27: 聚合氯化铝PAC | D27: 混凝 | E27: t | F27: 1100 | G27: 聚合氯化铝PAC-元-t | H27: 成本库
A28: PAM | B28: 材料 | C28: 聚丙烯酰胺PAM | D28: 助凝 | E28: t | F28: 7000 | G28: 聚丙烯酰胺pam | H28: 成本库
... A38: SOILT | B38: 外委 | C38: 土壤检测外委 | D38: 超标因子 | E38: 样 | F38: 150 | G38: 检测外委费-土壤水气危废 | H38: 施工自检。全项45项不适用此价
A39: RIG | B39: 机械 | C39: 成井钻机台班 | D39: 折旧2500+柴油×60L+司机 | E39: 台班 | F39: =2500+F4*60+F5 -> 3182.2 | G39: 台班公式 | H39: 卵石层成井。挖机不能成井
A40: SIGN | B40: 材料 | C40: 标识标牌 | D40: 铝板反光 | E40: 个 | F40: 180 | G40: 估价 | H40: 材料+制作。库内无同口径，不采用可研500元/个
A41: PIT | B41: 材料 | C41: 集水池砖砌体 | D41: 砖8.2千块+砂浆6.5t | E41: 座 | F41: =8.2*F20+6.5*F21 -> 4103.5 | G41: 砖+砂浆公式 | H41: 4×10×3 m侧壁。不采用可研30000元/座
A42: WASHB | B42: 材料 | C42: 洗车池砖砌沉淀体 | D42: 砖1.83千块+砂浆1.8t | E42: 座 | F42: =1.83*F20+1.8*F21 -> 990.9 | G42: 砖+砂浆公式 | H42: 侧池不过车主体，平台另计混凝土
A43: FULL | B43: 外委 | C43: 土壤全项检测外委 | D43: GB 36600表1的45项+石油烃 | E43: 样 | F43: 150 | G43: 检测外委费-土壤水气危废 | H43: 库内无全项独立价，暂用超标因子150元/样。不采用可研2800元/个，待实验室报价替换
A44: WB | B44: 材料 | C44: 地磅设备摊销 | D44: 100 t，12个月按购置1/3摊销 | E44: 台 | F44: 28000 | G44: 估价 | H44: 库内无地磅租赁价。购置约8万元，12个月摊销1/3。不是进厂过磅12元/t
A45: WBF | B45: 材料 | C45: 地磅基础 | D45: 混凝土基础+引坡 | E45: 台 | F45: =18*F17 -> 6210 | G45: C20×18 m³ | H45: 基础混凝土，单价引用C20
A47: F列输入为蓝字黄底。台班、车次、砖砌体为公式。清单消耗量通过VLOOKUP引用本表F列。改柴油价后，挖掘机、装载机、自卸车、压路机、吊车、筛分斗、冲洗、洒水、钻机、长途车次一起变。 地磅为场内100 t汽车衡，设备摊销28000元/台为估价。全项检测暂用150元/样，不是可研2800元/个。

Sheet 工程量计算
A1: 工程量计算。黄底为输入，绿字为公式。费用汇总工程量引用本表。本表只取可研方量和临建数量，不取投资估算单价。
A2: 来源：可研1.1.3、表4.3-1、表13.1-1数量列、第6章技术路线。勾稽差应为0。容重、运距、废水系数为假设，黄色可改。
A3: 编码 | B3: 名称 | C3: 数值 | D3: 单位 | E3: 公式/口径 | F3: 来源 | G3: 去向 | H3: 备注
A4: T01 | B4: 污染土方清挖筛分 | C4: 33728.15 | D4: m³ | E4: 输入 | F4: 可研1.1.3 / 表4.3-1 | G4: 清挖、筛分 | H4: 金宏+东升合计
A5: T02 | B5: 筛分卵石 | C5: 16499.79 | D5: m³ | E5: 输入 | F5: 可研1.1.3 | G5: 清洗、回填 | H5: 全部来自东升实业，金宏卵石为0
A6: T03 | B6: 筛分污染土壤 | C6: 17228.36 | D6: m³ | E6: 输入 | F6: 可研1.1.3 | G6: 含汞+水泥窑 | H6: 等于含汞+其他
A7: T04 | B7: 含汞污染土壤 | C7: 202.65 | D7: m³ | E7: 输入 | F7: 可研1.1.3 | G7: 安全处置 | H7: 单独转运
A8: T05 | B8: 水泥窑协同土壤 | C8: 17025.71 | D8: m³ | E8: 输入 | F8: 可研1.1.3 | G8: 水泥窑 | H8: 其他类型污染土壤
A9: T06 | B9: 天然容重 | C9: 1.6 | D9: t/m³ | E9: 输入 | F9: 可研未给实测容重 | G9: 吨位换算 | H9: 砂卵石地层假设1.6，黄色可改
A10: T07 | B10: 水泥窑运距 | C10: 40 | D10: km | E10: 输入 | F10: 可研未给接收窑 | G10: 密闭运输 | H10: 马祖镇至德阳/绵竹方向假设40 km
A11: T08 | B11: 含汞危废运距 | C11: 80 | D11: km | E11: 输入 | F11: 可研未给接收单位 | G11: 密闭运输 | H11: 川内持证单位假设80 km
A12: T09 | B12: 密闭车实载 | C12: 12 | D12: t/车 | E12: 输入 | F12: 15 t车实载 | G12: 车次 | H12: 与旺平模版同口径
A13: T10 | B13: 往返油耗系数 | C13: 0.32 | D13: L/km | E13: 输入 | F13: 旺平模版车次公式 | G13: 柴油 | H13: 单程油耗，公式按往返×2
A14: T11 | B14: 卵石清洗废水系数 | C14: 0.15 | D14: m³/m³ | E14: 输入 | F14: 无实测 | G14: 废水 | H14: 冲洗废水=卵石方量×系数
A15: T12 | B15: 临时办公生活用房 | C15: 500 | D15: m² | E15: 输入 | F15: 可研表13.1-1序号1.1数量 | G15: 临建 | H15: 只取数量，不取600元/m²
... A35: T32 | B35: 场内地磅 | C35: 2 | D35: 台 | E35: 输入 | F35: 两地块各1台 | G35: 出场计量 | H35: 可研7.5.6.2汽车衡在水泥厂。本条是场内100 t地磅，数量为假设
A36: 派生工程量（公式，绿色）。改黄色输入后自动重算。
A37: 编码 | B37: 名称 | C37: 数值 | D37: 单位 | E37: 公式/口径 | F37: 来源 | G37: 去向 | H37: 备注
A38: D01 | B38: 水泥窑处置吨位 | C38: =C8*C9 -> 27241.136 | D38: t | E38: T05×容重 | F38: 公式 | G38: 水泥窑、运输 | H38: 不采用可研按方计价
A39: D02 | B39: 含汞处置吨位 | C39: =C7*C9 -> 324.24 | D39: t | E39: T04×容重 | F39: 公式 | G39: 运输 | H39: 处置仍按立方米外委
A40: D03 | B40: 水泥窑运输周转量 | C40: =C8*C9*C10 -> 1089645.4 | D40: t·km | E40: 吨位×运距 | F40: 公式 | G40: 密闭运输 | H40: 运距黄色可改
A41: D04 | B41: 含汞运输周转量 | C41: =C7*C9*C11 -> 25939.2 | D41: t·km | E41: 吨位×运距 | F41: 公式 | G41: 密闭运输 | H41: 运距黄色可改
A42: D05 | B42: 水泥窑车次 | C42: =C8*C9/C12 -> 2270.0947 | D42: 车次 | E42: 吨位/实载 | F42: 公式 | G42: 运输校核 | H42: 15 t车实载12 t
A43: D06 | B43: 卵石清洗废水量 | C43: =C5*C14 -> 2474.9685 | D43: m³ | E43: 卵石方量×废水系数 | F43: 公式 | G43: 废水 | H43: 系数0.15为假设
A44: D07 | B44: 外购清洁土 | C44: =C6 -> 17228.36 | D44: m³ | E44: 等于筛分污染土壤 | F44: 公式 | G44: 回填 | H44: 外运土壤由清洁土补回
A45: D08 | B45: 监测井总深 | C45: =C24*C25 -> 200 | D45: m | E45: 口数×井深 | F45: 公式 | G45: 成井 | H45: 应为200 m
A46: D09 | B46: 筛分勾稽 | C46: =C6-C7-C8 -> 0 | D46: m³ | E46: T03-T04-T05 | F46: 公式 | G46: 校核 | H46: 应为0
A47: D10 | B47: 清挖勾稽 | C47: =C4-C5-C6 -> 0 | D47: m³ | E47: T01−T02−T03 | F47: 公式 | G47: 校核 | H47: 应为0
A49: 不含：基坑支护、降水（可研第14.2条明确未设计）、前期咨询、勘察、初设、施工图预算、环境监理、第三方效果评估服务费、招标代理、预备费、建设单位管理费。回填土壤监测和二次污染区域按施工自检列入。场内地磅与进厂过磅杂费不是同一项。
